{
  "id": 1230313,
  "url": "https://www.csfd.cz/film/1230313-susarny/",
  "name": "Sušárny",
  "screenings": {
    "Praha - Kino Světozor": [
      "2023-10-08T21:00:00.000Z"
    ]
  },
  "content": "Malé venkovské městečko je rájem pro dívku z města a zároveň klecí pro místní teenagerku. Dva paralelní příběhy, které se odehrávají mezi sušáky tabáku během léta zabarveného magickým realismem.\n\n\t\t\n\t\t\t\t(La Película)",
  "posterUrl": "https://image.pmgstatic.com/cache/resized/w140/files/images/film/posters/167/522/167522006_oy26sz.jpg"
}