{
  "id": 1290478,
  "url": "https://www.csfd.cz/film/1290478-zatracena-krvava-laska/",
  "name": "Zatracená krvavá láska",
  "screenings": {
    "Praha - Bio Oko": [
      "2024-08-04T16:30:00.000Z",
      "2024-08-06T18:00:00.000Z"
    ],
    "Praha - Cinema City Chodov": [
      "2024-07-31T21:50:00.000Z"
    ],
    "Praha - Cinema City Slovanský dům": [
      "2024-07-31T21:50:00.000Z"
    ],
    "Praha - Edison Filmhub": [
      "2024-07-31T21:30:00.000Z"
    ],
    "Praha - Kino Aero": [
      "2024-08-06T20:30:00.000Z"
    ],
    "Praha - Kino Kavalírka": [
      "2024-08-02T18:00:00.000Z"
    ],
    "Praha - Kino Pilotů": [
      "2024-07-31T21:10:00.000Z",
      "2024-08-01T21:20:00.000Z",
      "2024-08-03T21:20:00.000Z",
      "2024-08-05T21:00:00.000Z"
    ],
    "Praha - Kino Světozor": [
      "2024-07-31T20:15:00.000Z",
      "2024-08-01T20:15:00.000Z",
      "2024-08-02T20:45:00.000Z",
      "2024-08-03T21:00:00.000Z",
      "2024-08-04T20:45:00.000Z",
      "2024-08-06T20:15:00.000Z",
      "2024-08-07T20:45:00.000Z"
    ],
    "Praha - Komorní kino Evald": [
      "2024-08-02T18:00:00.000Z"
    ],
    "Praha - Přítomnost Boutique Cinema": [
      "2024-08-04T17:30:00.000Z"
    ]
  },
  "content": "Konec osmdesátek, vyprahlý americký zapadákov. Samotářská provozní posilovny Lou (Kristen Stewart) se bezhlavě zamiluje do Jackie (Katy O'Brian), nabušené kulturistky, která míří vyhrát mistrovství do Las Vegas. Vášnivá láska a německé steroidy vlijí ústřední dvojici do žil obrovskou dávku energie. V nekontrolovaném opojení se vydají za démonickým otcem Lou (Ed Harris) pomstít jednou provždy staré křivdy. Režisérka Rose Glass zelektrizovala Sundance i Berlinale neodolatelně podvratným thrillerem, který vám zvýší tepovku a vyplaví endorfiny.\n\n\t\t\n\t\t\t\t\t(Aerofilms)",
  "posterUrl": "https://image.pmgstatic.com/cache/resized/w140/files/images/film/posters/169/050/169050593_ts0aqu.jpg"
}