{
  "id": 1295100,
  "url": "https://www.csfd.cz/film/1295100-arquitectura-emocional-1959/",
  "name": "Arquitectura emocional 1959",
  "screenings": {
    "Praha - Kino Světozor": [
      "2023-10-03T18:00:00.000Z"
    ]
  },
  "content": "Hravý snímek odehrávající se v Madridu za Frankova režimu představuje, jakou roli můžou sehrát architektura a urbanistické uspořádání města v romantickém příběhu. Je říjen roku 1959, začátek zimního semestru a mladí studenti filozofie Sebas a Andrea pocházející z naprosto opačných socioekonomických prostředí se potkávají na lavičce v parku. Zatímco ona bydlí v bytovém domě v centru města hned vedle parku, jeho rodina se tísní v malém bytě v kolonii sociálního bydlení za městem. Architektura zde nevystupuje jako pouhá kulisa, nýbrž jako aktivní hybatel příběhu.\n\n\t\t\n\t\t\t\t(Film a Architektura)",
  "posterUrl": "https://image.pmgstatic.com/cache/resized/w140/files/images/film/posters/167/074/167074648_979075.jpg"
}