{
  "id": 1346630,
  "url": "https://www.csfd.cz/film/1346630-bratri/",
  "name": "Bratři",
  "screenings": {
    "Praha - Cinema City Flora": [
      "2023-11-21T21:00:00.000Z",
      "2023-11-22T21:00:00.000Z"
    ],
    "Praha - Cinema City Chodov": [
      "2023-11-21T16:10:00.000Z",
      "2023-11-21T19:00:00.000Z",
      "2023-11-21T21:50:00.000Z",
      "2023-11-22T16:10:00.000Z",
      "2023-11-22T19:00:00.000Z",
      "2023-11-22T21:50:00.000Z",
      "2023-11-23T16:20:00.000Z",
      "2023-11-23T19:10:00.000Z",
      "2023-11-24T16:20:00.000Z",
      "2023-11-24T19:10:00.000Z",
      "2023-11-25T16:20:00.000Z",
      "2023-11-25T19:10:00.000Z",
      "2023-11-26T16:20:00.000Z",
      "2023-11-26T19:10:00.000Z",
      "2023-11-27T16:20:00.000Z",
      "2023-11-27T19:10:00.000Z",
      "2023-11-28T16:20:00.000Z",
      "2023-11-28T19:10:00.000Z",
      "2023-11-29T16:20:00.000Z",
      "2023-11-29T19:10:00.000Z"
    ],
    "Praha - Cinema City Letňany": [
      "2023-11-21T17:40:00.000Z",
      "2023-11-21T20:30:00.000Z",
      "2023-11-22T17:40:00.000Z",
      "2023-11-22T20:30:00.000Z",
      "2023-11-23T21:20:00.000Z",
      "2023-11-24T21:20:00.000Z",
      "2023-11-25T21:20:00.000Z",
      "2023-11-26T21:20:00.000Z",
      "2023-11-27T21:20:00.000Z",
      "2023-11-28T21:20:00.000Z",
      "2023-11-29T21:20:00.000Z"
    ],
    "Praha - Cinema City Nový Smíchov": [
      "2023-11-21T17:45:00.000Z",
      "2023-11-21T20:30:00.000Z",
      "2023-11-22T17:45:00.000Z",
      "2023-11-22T20:30:00.000Z",
      "2023-11-23T21:50:00.000Z",
      "2023-11-24T21:50:00.000Z",
      "2023-11-25T21:50:00.000Z",
      "2023-11-26T21:50:00.000Z",
      "2023-11-27T21:50:00.000Z",
      "2023-11-28T21:50:00.000Z",
      "2023-11-29T21:50:00.000Z"
    ],
    "Praha - Cinema City Slovanský dům": [
      "2023-11-21T15:30:00.000Z",
      "2023-11-21T18:20:00.000Z",
      "2023-11-22T15:30:00.000Z",
      "2023-11-23T20:00:00.000Z",
      "2023-11-24T20:00:00.000Z",
      "2023-11-25T20:00:00.000Z",
      "2023-11-26T20:00:00.000Z",
      "2023-11-27T20:00:00.000Z",
      "2023-11-29T20:00:00.000Z"
    ],
    "Praha - Cinema City Zličín": [
      "2023-11-21T18:20:00.000Z",
      "2023-11-21T21:10:00.000Z",
      "2023-11-22T18:20:00.000Z",
      "2023-11-22T21:10:00.000Z",
      "2023-11-23T19:00:00.000Z",
      "2023-11-24T19:00:00.000Z",
      "2023-11-25T19:00:00.000Z",
      "2023-11-26T19:00:00.000Z",
      "2023-11-27T19:00:00.000Z",
      "2023-11-28T19:00:00.000Z",
      "2023-11-29T19:00:00.000Z"
    ]
  },
  "content": "Film líčí příběh dvou sourozenců, Abanga a Adiho, kteří jsou rodilí Malajsijci žijící v Pudu, Kuala Lumpuru, ale nemají průkaz totožnosti. Pudu bývalo odedávna známé svým tradičním trhem a prosperující komunitou, ale situace se změnila. Bratři čelí mnoha výzvám, včetně toho, že, kvůli chybějícím dokladům, nemají práva jako ostatní a nemohou si ani zažádat o pas nebo otevřít účet v bance. Starší Abang se narodil němý a jeho jediným cílem je tvrdě pracovat a vést stabilní život. Na druhé straně Adi se nechce poddat osudu a zaplete se do prodeje falešných průkazů, aby rychle vydělal peníze a dostali se s Abangem pryč. Nakonec jim se získáním úředních dokladů začne pomáhat Jin En, sociální pracovnice z nevládní organizace. Ale Jin En se stane tragická nehoda a Abang s Adim se opět ocitají v nesnázích.\n\n\t\t\n\t\t\t\t(Asean+3 Film Festival)",
  "posterUrl": "https://image.pmgstatic.com/cache/resized/w140/files/images/film/posters/167/979/167979227_gqb45f.jpg"
}