{
  "id": 1368394,
  "url": "https://www.csfd.cz/film/1368394-lenosice/",
  "name": "Lenošice",
  "screenings": {
    "Praha - Bio Oko": [
      "2024-02-18T15:00:00.000Z"
    ],
    "Praha - Kino Aero": [
      "2024-02-17T15:00:00.000Z"
    ]
  },
  "content": "Blobové, líná stvoření, žijí svůj poklidný život v lese. Při přechodovém rituálu obdrží semínko, které při kontaktu vykvete.\n\n\t\t\n\t\t\t\t(Zlín Film Festival)",
  "posterUrl": "data:image/gif;base64,R0lGODlhAQABAIAAAAAAAP///yH5BAEAAAAALAAAAAABAAEAAAIBRAA7"
}