{
  "id": 1395933,
  "url": "https://www.csfd.cz/film/1395933-nadhera-zivota/",
  "name": "Nádhera života",
  "screenings": {
    "Praha - Cinema City Chodov": [
      "2024-12-05T20:30:00.000Z",
      "2024-12-06T20:30:00.000Z",
      "2024-12-08T21:10:00.000Z",
      "2024-12-09T20:30:00.000Z",
      "2024-12-10T20:30:00.000Z",
      "2024-12-11T20:30:00.000Z"
    ],
    "Praha - Cinema City Slovanský dům": [
      "2024-12-05T19:40:00.000Z",
      "2024-12-06T19:40:00.000Z",
      "2024-12-07T19:40:00.000Z",
      "2024-12-08T19:40:00.000Z",
      "2024-12-09T19:40:00.000Z",
      "2024-12-10T19:40:00.000Z",
      "2024-12-11T19:40:00.000Z"
    ],
    "Praha - Kino MAT": [
      "2024-12-07T20:30:00.000Z"
    ],
    "Praha - Kino Radotín": [
      "2024-12-08T20:00:00.000Z"
    ]
  },
  "content": "Díky síle lásky se stává poslední rok života Franze Kafky jeho nejšťastnějším. Nikdy předtím si nedovolil prožívat intimitu tak silně jako teď, zatímco trpí tuberkulózou a je závislý na své přehnaně pozorné rodině. Ale světaznalá Dora Diamantová ho přijímá takového, jaký je. A on přijímá ji. Setkávají se v roce 1923 na pobřeží Baltského moře, kde se on zotavuje a ona pracuje v židovském Volksheimu. Společně odjedou do Berlína, a když se Franzův zdravotní stav prudce zhorší, tak do sanatoria v Rakousku. Necelý rok po jejich setkání Kafka umírá. Vzpomínky na jejich společně prožitý čas však budou Doru formovat po zbytek jejího života.\n\n\t\t\n\t\t\t\t\t(Film Europe)",
  "posterUrl": "https://image.pmgstatic.com/cache/resized/w140/files/images/film/posters/169/306/169306657_iz18wh.jpg"
}