{
  "id": 1400041,
  "url": "https://www.csfd.cz/film/1400041-sladke-sneni/",
  "name": "Sladké snění",
  "screenings": {
    "Praha - Edison Filmhub": [
      "2024-04-04T18:30:00.000Z"
    ]
  },
  "content": "Cukrovarnická plantáž kdesi v Nizozemské východní Indii. Po náhlé smrti majitele Jana se jeho žena Agathe zasazuje o návrat syna Cornelia z Evropy, aby převzal rodinný byznys. Proti tomu se ale staví domorodá pokojská Siti, která Janovi porodila nemanželského syna. Satira ve stylu snímků Rubena Östlunda z dob kolonialismu.\n\n\t\t\n\t\t\t\t(Dny evropského filmu)",
  "posterUrl": "https://image.pmgstatic.com/cache/resized/w140/files/images/film/posters/168/078/168078652_eaa2aa.jpg"
}