{
  "id": 1426315,
  "url": "https://www.csfd.cz/film/1426315-wavy-plavba-meho-zivota/",
  "name": "Wavy: Plavba mého života",
  "screenings": {
    "Praha - Kino Aero": [
      "2023-11-21T19:25:00.000Z"
    ]
  },
  "content": "Lyžařská odysea v kulisách mrazivých severních fjordů Norska. Dvojice freeriderů se na palubě lodi excentrického kapitána Crocse vydává k vysněnému pohoří. Své touhy upínají ke skalním věžím Kvænangstindan, které se zvedají z vln Norského moře a kde si Nikolai pamatuje, že před více než deseti lety viděl lyžařskou stopu… Film o přátelství, cestě do neznáma, ale hlavně plný neskutečně fantastických sjezdů!\n\n\t\t\n\t\t\t\t(Snow Film Fest)",
  "posterUrl": "data:image/gif;base64,R0lGODlhAQABAIAAAAAAAP///yH5BAEAAAAALAAAAAABAAEAAAIBRAA7"
}