{
  "id": 1587362,
  "url": "https://www.csfd.cz/film/1587362-hun-tun/",
  "name": "Hun Tun",
  "screenings": {
    "Praha - Kino Ponrepo": [
      "2024-12-18T18:00:00.000Z"
    ]
  },
  "content": "Zkušenost pozvolného sestupu po spirále vyčerpání, lemovaná farmaceutickými životabudiči, je vyprávěná v obrazech, které kombinují stop-motion s dalšími animačními technikami. Autobiograficky laděný popis prožitků se proplétá s taoistickým příběhem o mocném vládci chaosu Hun Tunovi, interpretovaném autorským voice-overem.\n\n\t\t\n\t\t\t\t(MFDF Ji.hlava)",
  "posterUrl": "data:image/gif;base64,R0lGODlhAQABAIAAAAAAAP///yH5BAEAAAAALAAAAAABAAEAAAIBRAA7"
}