{
  "id": 23053,
  "url": "https://www.csfd.cz/film/23053-patek-trinacteho/",
  "name": "Pátek třináctého",
  "screenings": {
    "Praha - Kino Aero": [
      "2024-09-13T18:00:00.000Z"
    ]
  },
  "content": "Vítejte v táboře Crystal Lake. Jeho historie je krvavá a místní říkají, že je prokletý. Je to dokonalé místo, kde může psychopat za svitu romantického úplňku zabíjet zamilované táborové vedoucí jednoho po druhém. Původní vyvražďovačka režiséra a producenta Seana S. Cunninghama vedla ke vzniku fenomenální filmové série a stovek imitací. Díky atraktivnímu obsazení (včetně mladého Kevina Bacona) a kreativnímu způsobu, jakým brutální syn zbožňující matky používá ostré nástroje, nepřestává tento klasický krvák napínat, inspirovat a děsit.\n\n\t\t\n\t\t\t\t\t(Magic Box)",
  "posterUrl": "https://image.pmgstatic.com/cache/resized/w140/files/images/film/posters/162/487/162487268_abae6a.jpg"
}