{
  "id": 24025,
  "url": "https://www.csfd.cz/film/24025-robin-hood/",
  "name": "Robin Hood",
  "screenings": {
    "Praha - Kino Ponrepo": [
      "2023-06-05T18:00:00.000Z"
    ]
  },
  "content": "Uprostřed velkorozpočtových středověkých slavností se král Richard vydává na křížovou výpravu a zanechává svého bratra, prince Johna, jako regenta. Ten se vzápětí ukáže jako krutý, chamtivý a proradný tyran. Vstupte do světa Robina Hooda, akrobatického ochránce utlačovaných, který se snaží dát věci do pořádku pomocí šermířských kousků a napínavých nebezpečenství!\n\n\t\t\n\t\t\t\t\t(Film Europe)",
  "posterUrl": "https://image.pmgstatic.com/cache/resized/w140/files/images/film/posters/166/795/166795524_823869.jpg"
}