{
  "id": 372325,
  "url": "https://www.csfd.cz/film/372325-socialisticky-zombi-mord/",
  "name": "Socialistický Zombi Mord",
  "screenings": {
    "Praha - Kino Balt": [
      "2024-07-03T18:30:00.000Z"
    ]
  },
  "content": "Sovietsky tajný experiment, ktorý mal slúžiť na paralyzovanie armády imperialistického nepriateľa socializmu rozšírením agresívnej smrteľnej nákazy (kódové meno Zaraza) sa vymkol spod kontroly a musel byť ukončený. Vinou súdruha neznámeho vojaka sa zvyšná vzorka bojového plynu dostala pod falošným označením dymovníc do konvoja inváznych vojsk varšavskej zmluvy smerujúceho na územie Slovenska. O niekoľko rokov neskôr sa tento plyn použije pri rutinnom stredoškolskom brannom cvičení a nakazí nič netušiacich študentov. Malá skupinka žiakov bojuje o prežitie, ich jediným problémom však nie sú len agresívni nakazení spolužiaci, ale aj školník (bývalý dôstojník SPECNAZ), ktorý sa snaží za každú cenu zabrániť hroziacej medzinárodnej blamáži.\n\n\t\t\n\t\t\t\t\t(oficiální text distributora)",
  "posterUrl": "https://image.pmgstatic.com/cache/resized/w140/files/images/film/posters/158/568/158568696_c9c2a1.jpg"
}