{
  "id": 4713,
  "url": "https://www.csfd.cz/film/4713-pan-prstenu-dve-veze/",
  "name": "Pán prstenů: Dvě věže",
  "screenings": {
    "Praha - Kino Aero": [
      "2024-04-27T15:00:00.000Z",
      "2024-05-04T15:00:00.000Z"
    ],
    "Praha - Kino Kavalírka": [
      "2024-04-03T19:00:00.000Z"
    ]
  },
  "content": "Po smrti Boromira a rozpadu Společenstva se cesty jeho členů rozdělily. Hobbit Frodo se svým sluhou Samem putují k Hoře Osudu, jen tam mohou sprovodit ze světa obávaný Prsten moci. Musí se však vypořádat se skřetem Glumem, který se snaží Prsten ukrást, ale hobiti ho přemůžou, spoutají a donutí ho, aby je vedl k bráně Mordoru. Aragorn s elfem Legolasem a trpaslíkem Gimlim se vydávají po stopě skřetů, aby osvobodili z jejich zajetí hobbity Smíška a Pippina. Mezitím však sílí moc temného pána Saurona, který se spojil se zrádným čarodějem Sarumanem a společně upínají všechny síly k získání Prstenu. Kdyby ho znovu získali, pak by byla Středozem definitivně odsouzena k zániku. Naše hrdiny tak čeká ještě dlouhé putování a mnohé nástrahy, než se jim podaří Prsten moci jednou provždy zničit.\n\n\t\t\n\t\t\t\t\t(TV Nova)",
  "posterUrl": "https://image.pmgstatic.com/cache/resized/w140/files/images/film/posters/158/600/158600807_ea3544.jpg"
}