{
  "id": 580941,
  "url": "https://www.csfd.cz/film/580941-bergmanuv-ostrov/",
  "name": "Bergmanův ostrov",
  "screenings": {
    "Praha - Bio Oko": [
      "2023-10-17T20:30:00.000Z"
    ]
  },
  "content": "Americký filmársky pár sa utiahne na ostrov, ktorý kedysi inšpiroval samotného Bergmana k napísaniu tých najlepších scenárov. Na pozadí divokého ostrova sa im však čoskoro začne stierať rozdiel medzi fikciou a realitou.\n\n\t\t\n\t\t\t\t(Arsenal83)",
  "posterUrl": "https://image.pmgstatic.com/cache/resized/w140/files/images/film/posters/165/527/165527863_87d2ae.jpg"
}