{
  "id": "617185-amundsen",
  "url": "https://www.csfd.cz/film/617185-amundsen/",
  "name": "Amundsen",
  "year": 2019,
  "screenings": {
    "Dlabačov": [
      "2019-12-29T20:00:00.000Z"
    ],
    "Edison Filmhub": [
      "2019-12-27T15:30:00.000Z",
      "2020-01-06T16:00:00.000Z"
    ],
    "Modřanský biograf": [
      "2019-12-27T20:00:00.000Z",
      "2019-12-28T17:30:00.000Z",
      "2019-12-29T20:00:00.000Z"
    ]
  },
  "content": "Posledný Viging. Muž, ktorý nevedel byť druhý. Aj takto býva označovaný Roald Amundsen, dobrodruh, ktorý zapĺňal prázdne miesta na mape sveta, ako prvý dobyl južný pól a dosiahol obidva póly zemegule. Aký ale v skutočnosti bol tento slávny Nór? Celovečerná snímka Amundsen zachytáva nielen jeho neuveriteľné výpravy do nepreskúmaných ľadových pustatín či polárne lety vzducholoďou, ale odhaľuje aj súkromie a kontroverznú osobnosť legendárneho objaviteľa vrátane menej známych skutočností, ako bol jeho vzťah s bratom alebo milostné aféry.(Bontonfilm SK)",
  "imdbUrl": "https://www.imdb.com/title/tt6054846/combined",
  "posterUrl": "https://img.csfd.cz/files/images/film/posters/163/930/163930534_72eeb8.jpg"
}
