{
  "id": 648236,
  "url": "https://www.csfd.cz/film/648236-pres-prsty/",
  "name": "Přes prsty",
  "screenings": {
    "Praha - Cinema City Slovanský dům": [
      "2024-09-20T16:20:00.000Z",
      "2024-09-21T18:40:00.000Z"
    ]
  },
  "content": "Příběh filmu Přes prsty se odehrává na beach volejbalových hřištích, ale nejen na nich. Linda (Petra Hřebíčková) a Pavla (Denisa Nesvačilová) jsou parťačky, které obětují beach volejbalu všechno. Tedy skoro všechno. Mladší Pavle tak trochu začínají tikat biologické hodiny a s přítelem Hynkem (Vojta Dyk) chce co nejdříve otěhotnět. To starší svobodná a bezdětná Linda nechápe. Zvlášť, když se jim podařilo kvalifikovat na mistrovství Evropy… Všechno ale stejně nakonec zamotá svérázný správce hřiště se zajímavou minulostí Jíra (Jiří Langmajer).\n\n\t\t\n\t\t\t\t\t(Cinemart)",
  "posterUrl": "https://image.pmgstatic.com/cache/resized/w140/files/images/film/posters/163/605/163605093_715572.png"
}