{
  "id": "709963-spindl-2",
  "url": "https://www.csfd.cz/film/709963-spindl-2/",
  "name": "Špindl 2",
  "year": 2019,
  "screenings": {
    "CineStar Praha - Anděl": [
      "2019-12-29T10:40:00.000Z",
      "2019-12-29T19:20:00.000Z",
      "2019-12-30T10:40:00.000Z",
      "2019-12-30T19:20:00.000Z",
      "2020-01-01T19:20:00.000Z"
    ],
    "CineStar Praha - Černý Most": [
      "2019-12-31T12:50:00.000Z",
      "2019-12-31T17:10:00.000Z"
    ],
    "Cinema City Chodov": [
      "2019-12-29T15:00:00.000Z",
      "2019-12-29T19:45:00.000Z",
      "2019-12-30T15:00:00.000Z",
      "2019-12-30T19:45:00.000Z",
      "2019-12-31T10:50:00.000Z",
      "2020-01-01T19:45:00.000Z"
    ],
    "Cinema City Letňany": [
      "2019-12-29T14:20:00.000Z",
      "2019-12-29T16:40:00.000Z",
      "2019-12-30T14:20:00.000Z",
      "2019-12-30T16:40:00.000Z",
      "2020-01-01T18:00:00.000Z"
    ],
    "Cinema City Nový Smíchov": [
      "2019-12-29T14:10:00.000Z",
      "2019-12-30T14:10:00.000Z"
    ],
    "Cinema City Zličín": [
      "2019-12-29T15:30:00.000Z",
      "2019-12-30T15:30:00.000Z",
      "2020-01-01T18:30:00.000Z"
    ],
    "Divadlo Za plotem": [
      "2020-01-16T15:00:00.000Z"
    ]
  },
  "content": "Silvie je úspěšná lékařka a věří, že konečně našla recept i na šťastný vztah. Renata je manželka známého spisovatele, ve svých kurzech dodává dalším ženám odvahu a sílu k lepšímu životu, ale v jejím vlastním životě jeden osudový prvek schází. Herečka a tanečnice Eliška stojí na začátku slibně rozjeté kariéry, ale komplikuje se jí vztah s přítelem – muzikantem... A chlapi z horské služby jsou vždy připraveni pomoci. Kde jinde by se všechny příběhy mohly protnout a vyřešit, než v zasněženém Špindlu?(Bohemia MP)",
  "imdbUrl": "https://www.imdb.com/title/tt10257924/combined",
  "posterUrl": "https://img.csfd.cz/files/images/film/posters/163/884/163884367_c98e36.jpg"
}
