{
  "id": "723700-all-inclusive",
  "url": "https://www.csfd.cz/film/723700-all-inclusive/",
  "name": "All Inclusive",
  "year": 2019,
  "screenings": {
    "Kino Pilotů": [
      "2020-01-26T19:00:00.000Z"
    ],
    "Světozor": [
      "2020-01-23T21:00:00.000Z",
      "2020-01-24T13:00:00.000Z"
    ]
  },
  "content": "Kalervo je celoživotní otloukánek. Vše se ale změní, když mu Annukka, žena, která ho miluje, dá dárek.(Festival krátkých filmů Praha)",
  "imdbUrl": "https://www.imdb.com/title/tt10219324/combined",
  "posterUrl": "https://img.csfd.cz/files/images/film/posters/163/471/163471846_42fa8c.jpg"
}
