{
  "id": "731743-stahni-a-zemres",
  "url": "https://www.csfd.cz/film/731743-stahni-a-zemres/",
  "name": "Stáhni a zemřeš",
  "year": 2019,
  "screenings": {
    "CineStar Praha - Černý Most": [
      "2019-12-11T21:30:00.000Z",
      "2019-12-12T21:15:00.000Z",
      "2019-12-13T21:15:00.000Z",
      "2019-12-14T21:15:00.000Z",
      "2019-12-16T21:15:00.000Z",
      "2019-12-17T21:15:00.000Z"
    ],
    "Cinema City Chodov": [
      "2019-12-11T16:50:00.000Z",
      "2019-12-11T21:15:00.000Z",
      "2019-12-12T16:50:00.000Z",
      "2019-12-12T22:00:00.000Z",
      "2019-12-13T16:50:00.000Z",
      "2019-12-13T22:00:00.000Z",
      "2019-12-14T16:50:00.000Z",
      "2019-12-14T22:00:00.000Z",
      "2019-12-15T16:50:00.000Z",
      "2019-12-15T22:00:00.000Z",
      "2019-12-16T16:50:00.000Z",
      "2019-12-16T22:00:00.000Z",
      "2019-12-17T16:50:00.000Z",
      "2019-12-17T22:00:00.000Z",
      "2019-12-18T16:50:00.000Z",
      "2019-12-18T22:00:00.000Z"
    ],
    "Cinema City Letňany": [
      "2019-12-11T19:20:00.000Z",
      "2019-12-12T18:00:00.000Z",
      "2019-12-13T18:00:00.000Z",
      "2019-12-14T18:00:00.000Z",
      "2019-12-15T18:00:00.000Z",
      "2019-12-15T22:00:00.000Z",
      "2019-12-16T18:00:00.000Z",
      "2019-12-17T18:00:00.000Z",
      "2019-12-18T18:00:00.000Z"
    ],
    "Cinema City Nový Smíchov": [
      "2019-12-11T22:15:00.000Z",
      "2019-12-12T21:20:00.000Z",
      "2019-12-13T21:20:00.000Z",
      "2019-12-14T21:20:00.000Z",
      "2019-12-15T21:20:00.000Z",
      "2019-12-16T21:20:00.000Z",
      "2019-12-17T21:20:00.000Z",
      "2019-12-18T21:20:00.000Z"
    ],
    "Cinema City Zličín": [
      "2019-12-11T20:40:00.000Z",
      "2019-12-13T22:00:00.000Z",
      "2019-12-14T22:00:00.000Z",
      "2019-12-15T22:10:00.000Z"
    ]
  },
  "content": "Parta přátel si pro legraci nainstaluje aplikaci, o které se tvrdí, že umí předpovědět čas zbývající do smrti. Je to trapný pokus o žert nebo již každému začal děsivý odpočet?(Vertical Ent.)",
  "imdbUrl": "https://www.imdb.com/title/tt10039344/combined",
  "posterUrl": "https://img.csfd.cz/files/images/film/posters/163/807/163807033_6b0adf.jpg",
  "trailerUrl": "https://www.youtube.com/watch?v=qQrwmBMLHIc"
}
