{
  "id": 904020,
  "url": "https://www.csfd.cz/film/904020-jabka/",
  "name": "Jabka",
  "screenings": {
    "Praha - Kino Radotín": [
      "2023-06-04T20:00:00.000Z"
    ]
  },
  "content": "Svět zasáhla záhadná pandemie. Lidé bez důvodu ztrácejí paměť. Nezbývá, než si pod bedlivým dohledem lékařů a psychologů znovu budovat novou identitu. Amnézie postihne i Arise, muže ve středním věku. Apatický muž začíná podstupovat absurdní terapii, která mu má otevřít novou životní perspektivu. Debutující Christos Nikou svým stylem patří k řecké divné vlně, ale do známé receptury přidává osvěžující prvky něžného melodramatu a hořké komedie o touze zapomenout. Jabka jsou groteskní portrét doby, která vnucuje lidem pochybné recepty na štěstí.\n\n\t\t\n\t\t\t\t\t(Artcam Films)",
  "posterUrl": "https://image.pmgstatic.com/cache/resized/w140/files/images/film/posters/165/568/165568573_b2f285.jpg"
}