{
  "id": 9756,
  "url": "https://www.csfd.cz/film/9756-kabinet-doktora-caligariho/",
  "name": "Kabinet doktora Caligariho",
  "screenings": {
    "Praha - Edison Filmhub": [
      "2024-10-31T20:00:00.000Z"
    ]
  },
  "content": "V malém severoněmeckém městě šíří Dr. Caligari strach a teror s pomocí Cesareho. Ve dne Caligari vystavuje Cesareho na veletrhu, kde v hypnóze předpovídá budoucnost. V noci však Caligariho otrok prochází městem a páchá na příkaz svého pána šílené vraždy. Když jedné noci zemře mladík, kterému Cesare předpověděl blížící se smrt, začne Francis podezírat Dr. Caligariho. Když Cesare unese Francisovu přítelkyni Jane, podezření se mění v jistotu. Tento filmový skvost je ukázkovým příkladem expresionistického filmu a přispěl k mezinárodnímu uznání německé kinematografie.\n\n\t\t\n\t\t\t\t\t(Film Europe)",
  "posterUrl": "https://image.pmgstatic.com/cache/resized/w140/files/images/film/posters/160/870/160870904_1dab07.png"
}