{
  "dateAndTime": "2023-01-17T00:18:29.973Z",
  "cinemas": [
    "Praha - CineStar Praha - Anděl",
    "Praha - CineStar Praha - Černý Most",
    "Praha - Bio Oko",
    "Praha - Cinema City Flora",
    "Praha - Cinema City Chodov",
    "Praha - Cinema City Letňany",
    "Praha - Cinema City Nový Smíchov",
    "Praha - Cinema City Slovanský dům",
    "Praha - Cinema City Zličín",
    "Praha - Divadlo Horní Počernice",
    "Praha - Divadlo Za plotem",
    "Praha - Dlabačov",
    "Praha - Dobeška",
    "Praha - Edison Filmhub",
    "Praha - Kasárna Karlín",
    "Praha - Kino Aero",
    "Praha - Kino Balt",
    "Praha - Kino Kavalírka",
    "Praha - Kino Lucerna",
    "Praha - Kino MAT",
    "Praha - Kino Petrohradská",
    "Praha - Kino Pilotů",
    "Praha - Kino Ponrepo",
    "Praha - Kino Radotín",
    "Praha - Kino Světozor",
    "Praha - Kino 35",
    "Praha - Komorní kino Evald",
    "Praha - Městská knihovna",
    "Praha - Modřanský biograf",
    "Praha - Premiere Cinemas Praha Hostivař",
    "Praha - Přítomnost Boutique Cinema",
    "Praha - Rock Café",
    "Praha - Spirála"
  ],
  "movies": [
    {
      "id": 762974,
      "name": "438 dní",
      "screenings": 1,
      "posterUrl": "https://image.pmgstatic.com/cache/resized/w140/files/images/film/posters/163/745/163745656_74d125.jpg",
      "cinemas": [
        13
      ]
    },
    {
      "id": 1134198,
      "name": "A do kuchyně!",
      "screenings": 3,
      "posterUrl": "https://image.pmgstatic.com/cache/resized/w140/files/images/film/posters/166/912/166912309_8ca414.png",
      "cinemas": [
        24,
        25
      ]
    },
    {
      "id": 1189888,
      "name": "A pak přišla láska...",
      "screenings": 3,
      "posterUrl": "https://image.pmgstatic.com/cache/resized/w140/files/images/film/posters/166/848/166848593_e64ba7.jpg",
      "cinemas": [
        2,
        10,
        26
      ]
    },
    {
      "id": 1198063,
      "name": "á-B-C-D-é-F-G-H-CH-í-JONESTOWN",
      "screenings": 2,
      "posterUrl": "https://image.pmgstatic.com/cache/resized/w140/files/images/film/posters/166/819/166819044_a329b0.jpg",
      "cinemas": [
        2,
        17
      ]
    },
    {
      "id": 976644,
      "name": "Adam Ondra: Posunout hranice",
      "screenings": 1,
      "posterUrl": "https://image.pmgstatic.com/cache/resized/w140/files/images/film/posters/166/757/166757501_83e786.png",
      "cinemas": [
        11
      ]
    },
    {
      "id": 1194880,
      "name": "Amerika",
      "screenings": 4,
      "posterUrl": "https://image.pmgstatic.com/cache/resized/w140/files/images/film/posters/166/886/166886038_ecc5ac.png",
      "cinemas": [
        12,
        21,
        25
      ]
    },
    {
      "id": 231649,
      "name": "Antikrist",
      "screenings": 1,
      "posterUrl": "https://image.pmgstatic.com/cache/resized/w140/files/images/film/posters/159/384/159384846_e60bc0.jpg",
      "cinemas": [
        23
      ]
    },
    {
      "id": 1634,
      "name": "Apokalypsa",
      "screenings": 1,
      "posterUrl": "https://image.pmgstatic.com/cache/resized/w140/files/images/film/posters/166/216/166216117_76353a.jpg",
      "cinemas": [
        19
      ]
    },
    {
      "id": 1073185,
      "name": "Aquafobie",
      "screenings": 1,
      "posterUrl": "https://image.pmgstatic.com/cache/resized/w140/files/images/film/posters/165/604/165604415_cf248b.jpg",
      "cinemas": [
        17
      ]
    },
    {
      "id": 822305,
      "name": "Arvéd",
      "screenings": 1,
      "posterUrl": "https://image.pmgstatic.com/cache/resized/w140/files/images/film/posters/166/399/166399386_dd1ee3.jpg",
      "cinemas": [
        21
      ]
    },
    {
      "id": 812327,
      "name": "Asterix a Obelix: Říše středu",
      "screenings": 2,
      "posterUrl": "https://image.pmgstatic.com/cache/resized/w140/files/images/film/posters/167/047/167047099_389ba3.png",
      "cinemas": [
        11
      ]
    },
    {
      "id": 4939,
      "name": "Ať žije republika",
      "screenings": 1,
      "posterUrl": "https://image.pmgstatic.com/cache/resized/w140/files/images/film/posters/158/597/158597745_76f7e4.jpg",
      "cinemas": [
        22
      ]
    },
    {
      "id": 277495,
      "name": "Avatar: The Way of Water",
      "screenings": 980,
      "posterUrl": "https://image.pmgstatic.com/cache/resized/w140/files/images/film/posters/166/840/166840794_0d238f.png",
      "cinemas": [
        0,
        1,
        3,
        4,
        5,
        6,
        7,
        8,
        10,
        15,
        19,
        21,
        29
      ]
    },
    {
      "id": 655006,
      "name": "Až zařve lev",
      "screenings": 2,
      "posterUrl": "https://image.pmgstatic.com/cache/resized/w140/files/images/film/posters/166/071/166071875_fd2f85.jpg",
      "cinemas": [
        19,
        27
      ]
    },
    {
      "id": 790059,
      "name": "Babylon",
      "screenings": 236,
      "posterUrl": "https://image.pmgstatic.com/cache/resized/w140/files/images/film/posters/166/985/166985370_da2107.jpg",
      "cinemas": [
        0,
        1,
        2,
        3,
        4,
        5,
        6,
        7,
        8,
        9,
        10,
        11,
        15,
        18,
        19,
        23,
        24,
        25,
        26,
        27,
        28,
        29,
        30
      ]
    },
    {
      "id": 822328,
      "name": "Bandité pro Baladu",
      "screenings": 1,
      "posterUrl": "https://image.pmgstatic.com/cache/resized/w140/files/images/film/posters/166/834/166834676_a0bfe9.jpg",
      "cinemas": [
        15
      ]
    },
    {
      "id": 1081372,
      "name": "BANGER.",
      "screenings": 2,
      "posterUrl": "https://image.pmgstatic.com/cache/resized/w140/files/images/film/posters/166/573/166573073_ace297.jpg",
      "cinemas": [
        16,
        21
      ]
    },
    {
      "id": 22118,
      "name": "Benjamin aneb Deník panice",
      "screenings": 1,
      "posterUrl": "https://image.pmgstatic.com/cache/resized/w140/files/images/film/posters/162/547/162547687_a5fff9.jpg",
      "cinemas": [
        22
      ]
    },
    {
      "id": 274205,
      "name": "Bezva chlap",
      "screenings": 1,
      "posterUrl": "https://image.pmgstatic.com/cache/resized/w140/files/images/film/posters/159/801/159801485_9d215a.jpg",
      "cinemas": [
        13
      ]
    },
    {
      "id": 1295542,
      "name": "Billie Eilish: Live at the O2 (Extended Cut)",
      "screenings": 6,
      "posterUrl": "https://image.pmgstatic.com/cache/resized/w140/files/images/film/posters/167/076/167076752_835054.jpg",
      "cinemas": [
        4,
        6,
        7,
        24,
        29,
        30
      ]
    },
    {
      "id": 13373,
      "name": "Bílý autobus",
      "screenings": 1,
      "posterUrl": "https://image.pmgstatic.com/cache/resized/w140/files/images/film/posters/163/655/163655275_3967c6.jpg",
      "cinemas": [
        22
      ]
    },
    {
      "id": 1170254,
      "name": "Blízko",
      "screenings": 30,
      "posterUrl": "https://image.pmgstatic.com/cache/resized/w140/files/images/film/posters/166/909/166909836_f8f786.jpg",
      "cinemas": [
        2,
        7,
        15,
        16,
        21,
        24,
        25,
        26
      ]
    },
    {
      "id": 221523,
      "name": "Bludný kruh",
      "screenings": 1,
      "posterUrl": "https://image.pmgstatic.com/cache/resized/w140/files/images/film/posters/160/848/160848797_22961a.jpg",
      "cinemas": [
        22
      ]
    },
    {
      "id": 351849,
      "name": "Boj sněžného pluhu s mafií",
      "screenings": 1,
      "posterUrl": "https://image.pmgstatic.com/cache/resized/w140/files/images/film/posters/158/990/158990168_64d416.jpg",
      "cinemas": [
        13
      ]
    },
    {
      "id": 1032154,
      "name": "Bombastický Johan",
      "screenings": 11,
      "posterUrl": "https://image.pmgstatic.com/cache/resized/w140/files/images/film/posters/167/078/167078256_e4f4d2.jpg",
      "cinemas": [
        7,
        11,
        13,
        17,
        18,
        19,
        26
      ]
    },
    {
      "id": 37429,
      "name": "Bouře nad Asií",
      "screenings": 1,
      "posterUrl": "https://image.pmgstatic.com/cache/resized/w140/files/images/film/posters/159/120/159120411_a16ba9.jpg",
      "cinemas": [
        22
      ]
    },
    {
      "id": 455626,
      "name": "Bratři Lumiérové",
      "screenings": 1,
      "posterUrl": "https://image.pmgstatic.com/cache/resized/w140/files/images/film/posters/162/467/162467927_364746.jpg",
      "cinemas": [
        11
      ]
    },
    {
      "id": 234833,
      "name": "Brundibáři - Těší mě",
      "screenings": 1,
      "cinemas": [
        19
      ]
    },
    {
      "id": 1295376,
      "name": "BTS: Yet to Come in Cinemas",
      "screenings": 21,
      "posterUrl": "https://image.pmgstatic.com/cache/resized/w140/files/images/film/posters/167/075/167075985_429c3c.jpg",
      "cinemas": [
        0,
        1,
        4,
        5,
        6,
        7,
        18,
        29
      ]
    },
    {
      "id": 1073804,
      "name": "Buko",
      "screenings": 1,
      "posterUrl": "https://image.pmgstatic.com/cache/resized/w140/files/images/film/posters/166/518/166518074_d2a06f.jpg",
      "cinemas": [
        19
      ]
    },
    {
      "id": 1912,
      "name": "Casablanca",
      "screenings": 1,
      "posterUrl": "https://image.pmgstatic.com/cache/resized/w140/files/images/film/posters/160/984/160984325_beb3e1.jpg",
      "cinemas": [
        17
      ]
    },
    {
      "id": 109948,
      "name": "Cena za nebezpečí",
      "screenings": 1,
      "posterUrl": "https://image.pmgstatic.com/cache/resized/w140/files/images/film/posters/019/191/19191870_4df097.jpg",
      "cinemas": [
        22
      ]
    },
    {
      "id": 2972,
      "name": "Černý Petr",
      "screenings": 1,
      "posterUrl": "https://image.pmgstatic.com/cache/resized/w140/files/images/film/posters/162/012/162012570_9e54f5.jpg",
      "cinemas": [
        22
      ]
    },
    {
      "id": 737286,
      "name": "Civilizace - Dobrá zpráva o konci světa",
      "screenings": 1,
      "posterUrl": "https://image.pmgstatic.com/cache/resized/w140/files/images/film/posters/166/625/166625062_f8feba.jpg",
      "cinemas": [
        27
      ]
    },
    {
      "id": 88170,
      "name": "Dealer",
      "screenings": 8,
      "posterUrl": "https://image.pmgstatic.com/cache/resized/w140/files/images/film/posters/158/440/158440630_a58753.jpg",
      "cinemas": [
        11,
        13,
        17,
        19,
        20
      ]
    },
    {
      "id": 227552,
      "name": "Dealer 2",
      "screenings": 6,
      "posterUrl": "https://image.pmgstatic.com/cache/resized/w140/files/images/film/posters/160/782/160782739_dc65bb.jpg",
      "cinemas": [
        11,
        13,
        19,
        20
      ]
    },
    {
      "id": 227553,
      "name": "Dealer 3",
      "screenings": 6,
      "posterUrl": "https://image.pmgstatic.com/cache/resized/w140/files/images/film/posters/160/782/160782674_ec15a5.jpg",
      "cinemas": [
        11,
        13,
        19,
        20
      ]
    },
    {
      "id": 104978,
      "name": "Den hněvu",
      "screenings": 1,
      "posterUrl": "https://image.pmgstatic.com/cache/resized/w140/files/images/film/posters/160/283/160283721_2538aa.jpg",
      "cinemas": [
        22
      ]
    },
    {
      "id": 1116272,
      "name": "Divnosvět",
      "screenings": 15,
      "posterUrl": "https://image.pmgstatic.com/cache/resized/w140/files/images/film/posters/166/670/166670244_bd8bc7.jpg",
      "cinemas": [
        4,
        5,
        6,
        8
      ]
    },
    {
      "id": 16621,
      "name": "Dobrodružství Priscilly, královny pouště",
      "screenings": 1,
      "posterUrl": "https://image.pmgstatic.com/cache/resized/w140/files/images/film/posters/159/417/159417468_5f3f6c.jpg",
      "cinemas": [
        15
      ]
    },
    {
      "id": 28675,
      "name": "Doručovací služba čarodějky Kiki",
      "screenings": 24,
      "posterUrl": "https://image.pmgstatic.com/cache/resized/w140/files/images/film/posters/166/976/166976080_be680f.jpg",
      "cinemas": [
        2,
        3,
        4,
        10,
        11,
        15,
        17,
        20,
        23,
        24
      ]
    },
    {
      "id": 1142590,
      "name": "Dreaming Walls: Hotel Chelsea",
      "screenings": 2,
      "posterUrl": "https://image.pmgstatic.com/cache/resized/w140/files/images/film/posters/166/827/166827594_9b9b2f.jpg",
      "cinemas": [
        2,
        11
      ]
    },
    {
      "id": 10199,
      "name": "Duch",
      "screenings": 1,
      "posterUrl": "https://image.pmgstatic.com/cache/resized/w140/files/images/film/posters/159/527/159527693_7aba87.jpg",
      "cinemas": [
        15
      ]
    },
    {
      "id": 785609,
      "name": "Elvis",
      "screenings": 1,
      "posterUrl": "https://image.pmgstatic.com/cache/resized/w140/files/images/film/posters/166/325/166325733_761956.jpg",
      "cinemas": [
        24
      ]
    },
    {
      "id": 1113932,
      "name": "Emigranti",
      "screenings": 8,
      "posterUrl": "https://image.pmgstatic.com/cache/resized/w140/files/images/film/posters/167/021/167021674_55c4bf.jpg",
      "cinemas": [
        7,
        13,
        18,
        19,
        26
      ]
    },
    {
      "id": 1113256,
      "name": "EOS: Dánský sběratel - Delacroix až Gauguin",
      "screenings": 1,
      "posterUrl": "https://image.pmgstatic.com/cache/resized/w140/files/images/film/posters/166/826/166826878_2c5b9d.png",
      "cinemas": [
        11
      ]
    },
    {
      "id": 1041408,
      "name": "EOS: Slunečnice",
      "screenings": 1,
      "posterUrl": "https://image.pmgstatic.com/cache/resized/w140/files/images/film/posters/166/229/166229817_cb98dd.png",
      "cinemas": [
        11
      ]
    },
    {
      "id": 1081018,
      "name": "Fabelmanovi",
      "screenings": 42,
      "posterUrl": "https://image.pmgstatic.com/cache/resized/w140/files/images/film/posters/166/835/166835677_e72d45.png",
      "cinemas": [
        4,
        5,
        6,
        7,
        15,
        24,
        27,
        30
      ]
    },
    {
      "id": 226075,
      "name": "Ferda Mravenec - Příhody brouka Pytlíka",
      "screenings": 1,
      "cinemas": [
        22
      ]
    },
    {
      "id": 906708,
      "name": "Film roku",
      "screenings": 1,
      "posterUrl": "https://image.pmgstatic.com/cache/resized/w140/files/images/film/posters/166/138/166138497_1a0332.jpg",
      "cinemas": [
        11
      ]
    },
    {
      "id": 326977,
      "name": "Frank",
      "screenings": 1,
      "posterUrl": "https://image.pmgstatic.com/cache/resized/w140/files/images/film/posters/158/604/158604439_d323ad.jpg",
      "cinemas": [
        20
      ]
    },
    {
      "id": 1099881,
      "name": "Gekidžóban Swort Art Online: Progressive hoši naki joru no Aria",
      "screenings": 9,
      "posterUrl": "https://image.pmgstatic.com/cache/resized/w140/files/images/film/posters/165/793/165793510_c99ec2.jpg",
      "cinemas": [
        4,
        6,
        7
      ]
    },
    {
      "id": 914032,
      "name": "Grand Prix",
      "screenings": 6,
      "posterUrl": "https://image.pmgstatic.com/cache/resized/w140/files/images/film/posters/166/680/166680356_29c439.jpg",
      "cinemas": [
        0,
        26,
        27
      ]
    },
    {
      "id": 1052394,
      "name": "Haut et fort",
      "screenings": 1,
      "posterUrl": "https://image.pmgstatic.com/cache/resized/w140/files/images/film/posters/166/942/166942738_5993ed.jpg",
      "cinemas": [
        26
      ]
    },
    {
      "id": 1097250,
      "name": "Hlasy pro prezidenta aneb Pokus o kontrarevoluci",
      "screenings": 1,
      "posterUrl": "data:image/gif;base64,R0lGODlhAQABAIAAAAAAAP///yH5BAEAAAAALAAAAAABAAEAAAIBRAA7",
      "cinemas": [
        24
      ]
    },
    {
      "id": 1131253,
      "name": "Hodně štěstí, pane Veliký",
      "screenings": 1,
      "posterUrl": "https://image.pmgstatic.com/cache/resized/w140/files/images/film/posters/166/403/166403943_f5de9f.jpg",
      "cinemas": [
        11
      ]
    },
    {
      "id": 13456,
      "name": "Hrad opic",
      "screenings": 1,
      "posterUrl": "https://image.pmgstatic.com/cache/resized/w140/files/images/film/posters/164/691/164691324_379fc9.jpg",
      "cinemas": [
        25
      ]
    },
    {
      "id": 914035,
      "name": "Hranice lásky",
      "screenings": 21,
      "posterUrl": "https://image.pmgstatic.com/cache/resized/w140/files/images/film/posters/166/420/166420838_fb5eac.jpg",
      "cinemas": [
        0,
        11
      ]
    },
    {
      "id": 16366,
      "name": "Hříšný tanec",
      "screenings": 2,
      "posterUrl": "https://image.pmgstatic.com/cache/resized/w140/files/images/film/posters/000/014/14107_1dd808.jpg",
      "cinemas": [
        15
      ]
    },
    {
      "id": 710346,
      "name": "Il Boemo",
      "screenings": 12,
      "posterUrl": "https://image.pmgstatic.com/cache/resized/w140/files/images/film/posters/166/645/166645293_796c61.jpg",
      "cinemas": [
        2,
        21,
        24,
        26,
        27
      ]
    },
    {
      "id": 1033776,
      "name": "Já, hrobař",
      "screenings": 1,
      "posterUrl": "https://image.pmgstatic.com/cache/resized/w140/files/images/film/posters/166/672/166672183_f6d6cb.jpg",
      "cinemas": [
        14
      ]
    },
    {
      "id": 130694,
      "name": "Jak krtek ke kalhotkám přišel",
      "screenings": 1,
      "posterUrl": "https://image.pmgstatic.com/cache/resized/w140/files/images/film/posters/000/396/396265_752c6b.jpg",
      "cinemas": [
        22
      ]
    },
    {
      "id": 221382,
      "name": "Jak štěňátko chtělo malé pejsky",
      "screenings": 1,
      "posterUrl": "https://image.pmgstatic.com/cache/resized/w140/files/images/film/posters/000/047/47927_d34b26.jpg",
      "cinemas": [
        19
      ]
    },
    {
      "id": 1170287,
      "name": "Je mi ze sebe špatně",
      "screenings": 10,
      "posterUrl": "https://image.pmgstatic.com/cache/resized/w140/files/images/film/posters/167/078/167078286_80a594.jpg",
      "cinemas": [
        7,
        11,
        13,
        17,
        18,
        19,
        26
      ]
    },
    {
      "id": 270832,
      "name": "Jehovova pomsta",
      "screenings": 1,
      "posterUrl": "https://image.pmgstatic.com/cache/resized/w140/files/images/film/posters/000/064/64273_b58077.jpg",
      "cinemas": [
        31
      ]
    },
    {
      "id": 1168560,
      "name": "Kapka v moři",
      "screenings": 1,
      "posterUrl": "data:image/gif;base64,R0lGODlhAQABAIAAAAAAAP///yH5BAEAAAAALAAAAAABAAEAAAIBRAA7",
      "cinemas": [
        17
      ]
    },
    {
      "id": 1180761,
      "name": "KaprKód",
      "screenings": 1,
      "posterUrl": "https://image.pmgstatic.com/cache/resized/w140/files/images/film/posters/166/888/166888685_76d92b.jpg",
      "cinemas": [
        11
      ]
    },
    {
      "id": 36845,
      "name": "Každý den kromě Vánoc",
      "screenings": 1,
      "posterUrl": "data:image/gif;base64,R0lGODlhAQABAIAAAAAAAP///yH5BAEAAAAALAAAAAABAAEAAAIBRAA7",
      "cinemas": [
        22
      ]
    },
    {
      "id": 1060884,
      "name": "Když promluvila",
      "screenings": 9,
      "posterUrl": "https://image.pmgstatic.com/cache/resized/w140/files/images/film/posters/166/867/166867617_bd6e6c.jpg",
      "cinemas": [
        2,
        15,
        18,
        27
      ]
    },
    {
      "id": 389064,
      "name": "Kocour v botách: Poslední přání",
      "screenings": 336,
      "posterUrl": "https://image.pmgstatic.com/cache/resized/w140/files/images/film/posters/166/887/166887811_a46ea6.jpg",
      "cinemas": [
        0,
        1,
        3,
        4,
        5,
        6,
        7,
        8,
        11,
        21,
        23,
        25,
        29
      ]
    },
    {
      "id": 1170279,
      "name": "Korzet",
      "screenings": 1,
      "posterUrl": "https://image.pmgstatic.com/cache/resized/w140/files/images/film/posters/166/429/166429002_746994.jpg",
      "cinemas": [
        15
      ]
    },
    {
      "id": 71924,
      "name": "Království - Série 1",
      "screenings": 3,
      "posterUrl": "https://image.pmgstatic.com/cache/resized/w140/files/images/film/posters/166/708/166708064_2da697.jpg",
      "cinemas": [
        20
      ]
    },
    {
      "id": 130730,
      "name": "Krtek v Zoo",
      "screenings": 1,
      "posterUrl": "https://image.pmgstatic.com/cache/resized/w140/files/images/film/posters/000/036/36581_55f549.jpg",
      "cinemas": [
        19
      ]
    },
    {
      "id": 1246111,
      "name": "Kůň",
      "screenings": 3,
      "posterUrl": "https://image.pmgstatic.com/cache/resized/w140/files/images/film/posters/166/905/166905355_9360a1.png",
      "cinemas": [
        11,
        19,
        26
      ]
    },
    {
      "id": 1210372,
      "name": "Kunstkamera",
      "screenings": 1,
      "posterUrl": "https://image.pmgstatic.com/cache/resized/w140/files/images/film/posters/166/889/166889327_6cc994.jpg",
      "cinemas": [
        11
      ]
    },
    {
      "id": 1142876,
      "name": "Kvík",
      "screenings": 2,
      "posterUrl": "https://image.pmgstatic.com/cache/resized/w140/files/images/film/posters/166/793/166793176_a5b061.jpg",
      "cinemas": [
        11,
        17
      ]
    },
    {
      "id": 1247468,
      "name": "Letní světlo, a pak přijde noc",
      "screenings": 8,
      "posterUrl": "https://image.pmgstatic.com/cache/resized/w140/files/images/film/posters/166/912/166912777_7d6130.jpg",
      "cinemas": [
        7,
        11,
        13,
        17,
        19,
        26
      ]
    },
    {
      "id": 1202836,
      "name": "Lhář na plný úvazek",
      "screenings": 144,
      "posterUrl": "https://image.pmgstatic.com/cache/resized/w140/files/images/film/posters/166/978/166978348_799fa9.jpg",
      "cinemas": [
        3,
        4,
        5,
        6,
        7,
        8
      ]
    },
    {
      "id": 32198,
      "name": "Lola běží o život",
      "screenings": 1,
      "posterUrl": "https://image.pmgstatic.com/cache/resized/w140/files/images/film/posters/162/298/162298073_c94dcd.jpg",
      "cinemas": [
        15
      ]
    },
    {
      "id": 1136622,
      "name": "M3GAN",
      "screenings": 256,
      "posterUrl": "https://image.pmgstatic.com/cache/resized/w140/files/images/film/posters/166/935/166935691_6b643c.jpg",
      "cinemas": [
        0,
        1,
        3,
        4,
        5,
        6,
        7,
        8,
        10,
        11,
        29
      ]
    },
    {
      "id": 431725,
      "name": "Máma má raka",
      "screenings": 1,
      "posterUrl": "https://image.pmgstatic.com/cache/resized/w140/files/images/film/posters/160/998/160998318_d2112d.jpg",
      "cinemas": [
        31
      ]
    },
    {
      "id": 9342,
      "name": "Marketa Lazarová",
      "screenings": 1,
      "posterUrl": "https://image.pmgstatic.com/cache/resized/w140/files/images/film/posters/000/434/434837_af1896.jpg",
      "cinemas": [
        22
      ]
    },
    {
      "id": 1074654,
      "name": "Menu",
      "screenings": 17,
      "posterUrl": "https://image.pmgstatic.com/cache/resized/w140/files/images/film/posters/166/850/166850243_33fd43.jpg",
      "cinemas": [
        2,
        3,
        11,
        15,
        21,
        24,
        30
      ]
    },
    {
      "id": 1168558,
      "name": "Mia & Liki",
      "screenings": 1,
      "posterUrl": "https://image.pmgstatic.com/cache/resized/w140/files/images/film/posters/166/226/166226809_e2028a.jpg",
      "cinemas": [
        17
      ]
    },
    {
      "id": 1206246,
      "name": "Michael Kocáb – rocker versus politik",
      "screenings": 1,
      "posterUrl": "https://image.pmgstatic.com/cache/resized/w140/files/images/film/posters/166/450/166450726_7d8d13.jpg",
      "cinemas": [
        14
      ]
    },
    {
      "id": 1184885,
      "name": "Mikulášovy patálie: Jak to celé začalo",
      "screenings": 9,
      "posterUrl": "https://image.pmgstatic.com/cache/resized/w140/files/images/film/posters/166/890/166890136_566033.jpg",
      "cinemas": [
        2,
        15,
        18,
        24,
        25,
        26
      ]
    },
    {
      "id": 392704,
      "url": "https://www.csfd.cz/film/392704-mimoni-2-padouch-prichazi/",
      "name": "Mimoni 2: Padouch přichází",
      "screenings": {
        "Praha - Spirála": [
          "2023-01-22T10:30:00.000Z"
        ]
      }
    },
    {
      "id": 37980,
      "name": "Moje noc s Maud",
      "screenings": 1,
      "posterUrl": "https://image.pmgstatic.com/cache/resized/w140/files/images/film/posters/161/081/161081443_0c4536.jpg",
      "cinemas": [
        22
      ]
    },
    {
      "id": 673538,
      "name": "Monetovy lekníny - magie vody a světla",
      "screenings": 1,
      "posterUrl": "https://image.pmgstatic.com/cache/resized/w140/files/images/film/posters/163/379/163379490_a8b618.png",
      "cinemas": [
        19
      ]
    },
    {
      "id": 4742,
      "name": "Mrtvý muž",
      "screenings": 1,
      "posterUrl": "https://image.pmgstatic.com/cache/resized/w140/files/images/film/posters/162/481/162481992_4a1d89.jpg",
      "cinemas": [
        24
      ]
    },
    {
      "id": 1250762,
      "name": "Mumie",
      "screenings": 1,
      "posterUrl": "https://image.pmgstatic.com/cache/resized/w140/files/images/film/posters/166/964/166964377_618e7d.jpg",
      "cinemas": [
        29
      ]
    },
    {
      "id": 1234487,
      "name": "Munch – láska, duchové a upíří ženy",
      "screenings": 2,
      "posterUrl": "https://image.pmgstatic.com/cache/resized/w140/files/images/film/posters/166/752/166752654_0c15bd.png",
      "cinemas": [
        11,
        27
      ]
    },
    {
      "id": 39012,
      "name": "Muž a žena",
      "screenings": 1,
      "posterUrl": "https://image.pmgstatic.com/cache/resized/w140/files/images/film/posters/000/023/23428_53756b.jpg",
      "cinemas": [
        22
      ]
    },
    {
      "id": 39013,
      "name": "Muž a žena po 20 letech",
      "screenings": 1,
      "posterUrl": "https://image.pmgstatic.com/cache/resized/w140/files/images/film/posters/166/110/166110320_e467b7.jpg",
      "cinemas": [
        22
      ]
    },
    {
      "id": 1146292,
      "name": "Muž jménem Otto",
      "screenings": 2,
      "posterUrl": "https://image.pmgstatic.com/cache/resized/w140/files/images/film/posters/167/043/167043580_75d096.jpg",
      "cinemas": [
        11
      ]
    },
    {
      "id": 898350,
      "name": "Muži na pokraji nervového zhroucení",
      "screenings": 1,
      "posterUrl": "https://image.pmgstatic.com/cache/resized/w140/files/images/film/posters/166/233/166233640_0cd81e.jpg",
      "cinemas": [
        11
      ]
    },
    {
      "id": 7570,
      "name": "Na Hromnice o den více",
      "screenings": 1,
      "posterUrl": "https://image.pmgstatic.com/cache/resized/w140/files/images/film/posters/164/500/164500458_cd40e2.jpg",
      "cinemas": [
        15
      ]
    },
    {
      "id": 1255925,
      "name": "Na konci nějak pojmenovat ty věci aneb Zkurvených 294,5 km",
      "screenings": 1,
      "posterUrl": "data:image/gif;base64,R0lGODlhAQABAIAAAAAAAP///yH5BAEAAAAALAAAAAABAAEAAAIBRAA7",
      "cinemas": [
        22
      ]
    },
    {
      "id": 1294658,
      "name": "Navždy za Dynamo",
      "screenings": 7,
      "posterUrl": "https://image.pmgstatic.com/cache/resized/w140/files/images/film/posters/167/071/167071786_0741a9.jpg",
      "cinemas": [
        1
      ]
    },
    {
      "id": 726250,
      "name": "Největší dar",
      "screenings": 8,
      "posterUrl": "https://image.pmgstatic.com/cache/resized/w140/files/images/film/posters/166/793/166793727_bf5232.jpg",
      "cinemas": [
        4,
        32
      ]
    },
    {
      "id": 14654,
      "name": "Nemocnice Britania",
      "screenings": 1,
      "posterUrl": "https://image.pmgstatic.com/cache/resized/w140/files/images/film/posters/166/826/166826813_d46341.jpg",
      "cinemas": [
        22
      ]
    },
    {
      "id": 331261,
      "name": "Není čas zemřít",
      "screenings": 1,
      "posterUrl": "https://image.pmgstatic.com/cache/resized/w140/files/images/film/posters/165/648/165648860_534f85.jpg",
      "cinemas": [
        11
      ]
    },
    {
      "id": 1052467,
      "name": "Neuvěřitelné, ale pravdivé",
      "screenings": 2,
      "posterUrl": "https://image.pmgstatic.com/cache/resized/w140/files/images/film/posters/166/943/166943421_475a2e.jpg",
      "cinemas": [
        2,
        14
      ]
    },
    {
      "id": 1182274,
      "name": "Nic",
      "screenings": 7,
      "posterUrl": "https://image.pmgstatic.com/cache/resized/w140/files/images/film/posters/167/078/167078254_ad46df.jpg",
      "cinemas": [
        7,
        11,
        13,
        17,
        26
      ]
    },
    {
      "id": 1078266,
      "name": "Nosoroh",
      "screenings": 1,
      "posterUrl": "https://image.pmgstatic.com/cache/resized/w140/files/images/film/posters/166/232/166232164_72aa5e.jpg",
      "cinemas": [
        2
      ]
    },
    {
      "id": 205824,
      "name": "O Dorotce - Dorotka a papoušek",
      "screenings": 3,
      "cinemas": [
        19
      ]
    },
    {
      "id": 220946,
      "name": "O kocouru Mikešovi a jeho přátelích - Jak Mikeš zachránil Bobeše",
      "screenings": 2,
      "cinemas": [
        19
      ]
    },
    {
      "id": 1059883,
      "name": "Oběť",
      "screenings": 2,
      "posterUrl": "https://image.pmgstatic.com/cache/resized/w140/files/images/film/posters/166/582/166582891_95ba05.jpg",
      "cinemas": [
        18,
        21
      ]
    },
    {
      "id": 980996,
      "name": "Ono",
      "screenings": 12,
      "posterUrl": "https://image.pmgstatic.com/cache/resized/w140/files/images/film/posters/167/009/167009392_062da0.jpg",
      "cinemas": [
        7,
        11,
        13,
        16,
        18,
        26
      ]
    },
    {
      "id": 976063,
      "name": "Operace Fortune: Ruse de guerre",
      "screenings": 160,
      "posterUrl": "https://image.pmgstatic.com/cache/resized/w140/files/images/film/posters/166/964/166964391_9b914c.jpg",
      "cinemas": [
        0,
        1,
        2,
        3,
        4,
        5,
        6,
        7,
        8,
        11,
        21,
        24,
        29,
        30
      ]
    },
    {
      "id": 1028089,
      "name": "Osm hor",
      "screenings": 45,
      "posterUrl": "https://image.pmgstatic.com/cache/resized/w140/files/images/film/posters/166/976/166976055_411ff4.jpg",
      "cinemas": [
        0,
        2,
        7,
        15,
        21,
        24,
        26,
        27,
        30
      ]
    },
    {
      "id": 6664,
      "name": "Ostře sledované vlaky",
      "screenings": 1,
      "posterUrl": "https://image.pmgstatic.com/cache/resized/w140/files/images/film/posters/162/648/162648983_73d38f.jpg",
      "cinemas": [
        22
      ]
    },
    {
      "id": 1105807,
      "name": "Ostrov",
      "screenings": 5,
      "posterUrl": "https://image.pmgstatic.com/cache/resized/w140/files/images/film/posters/166/876/166876790_ee57b8.jpg",
      "cinemas": [
        0,
        1,
        9,
        11,
        29
      ]
    },
    {
      "id": 5407,
      "name": "Osvícení",
      "screenings": 1,
      "posterUrl": "https://image.pmgstatic.com/cache/resized/w140/files/images/film/posters/158/083/158083521_e7e712.jpg",
      "cinemas": [
        15
      ]
    },
    {
      "id": 193257,
      "name": "Pac a pusu",
      "screenings": 1,
      "posterUrl": "https://image.pmgstatic.com/cache/resized/w140/files/images/film/posters/164/337/164337745_a0aaf9.jpg",
      "cinemas": [
        22
      ]
    },
    {
      "id": 4713,
      "name": "Pán prstenů: Dvě věže",
      "screenings": 1,
      "posterUrl": "https://image.pmgstatic.com/cache/resized/w140/files/images/film/posters/158/600/158600807_ea3544.jpg",
      "cinemas": [
        19
      ]
    },
    {
      "id": 1033955,
      "name": "Paní Harrisová jede do Paříže",
      "screenings": 1,
      "posterUrl": "https://image.pmgstatic.com/cache/resized/w140/files/images/film/posters/166/662/166662798_bf82b4.jpg",
      "cinemas": [
        11
      ]
    },
    {
      "id": 754354,
      "name": "Párty Hárd",
      "screenings": 1,
      "posterUrl": "https://image.pmgstatic.com/cache/resized/w140/files/images/film/posters/163/666/163666544_84aa02.jpg",
      "cinemas": [
        31
      ]
    },
    {
      "id": 1052550,
      "name": "Párty Hárder: Summer Massacre",
      "screenings": 1,
      "posterUrl": "https://image.pmgstatic.com/cache/resized/w140/files/images/film/posters/166/364/166364241_ffad31.jpg",
      "cinemas": [
        31
      ]
    },
    {
      "id": 1245744,
      "name": "Pathaan",
      "screenings": 9,
      "posterUrl": "https://image.pmgstatic.com/cache/resized/w140/files/images/film/posters/166/840/166840616_649e52.jpg",
      "cinemas": [
        4,
        6,
        7
      ]
    },
    {
      "id": 18342,
      "name": "Pavoučí teror",
      "screenings": 1,
      "posterUrl": "https://image.pmgstatic.com/cache/resized/w140/files/images/film/posters/000/320/320785_3cd943.jpg",
      "cinemas": [
        16
      ]
    },
    {
      "id": 1199120,
      "name": "Piargy",
      "screenings": 13,
      "posterUrl": "https://image.pmgstatic.com/cache/resized/w140/files/images/film/posters/166/967/166967576_4916a5.jpg",
      "cinemas": [
        18,
        19,
        23,
        26
      ]
    },
    {
      "id": 976645,
      "name": "Planeta Praha",
      "screenings": 1,
      "posterUrl": "https://image.pmgstatic.com/cache/resized/w140/files/images/film/posters/166/429/166429031_1914c3.jpg",
      "cinemas": [
        19
      ]
    },
    {
      "id": 107026,
      "name": "Pojďte pane, budeme si hrát - Psí kusy",
      "screenings": 1,
      "posterUrl": "https://image.pmgstatic.com/cache/resized/w140/files/images/film/posters/000/321/321898_560fed.jpg",
      "cinemas": [
        22
      ]
    },
    {
      "id": 270365,
      "name": "Pokoj",
      "screenings": 1,
      "posterUrl": "https://image.pmgstatic.com/cache/resized/w140/files/images/film/posters/158/708/158708214_5e75ab.jpg",
      "cinemas": [
        16
      ]
    },
    {
      "id": 1031431,
      "name": "Posedlost",
      "screenings": 7,
      "posterUrl": "https://image.pmgstatic.com/cache/resized/w140/files/images/film/posters/166/642/166642286_d20be4.jpg",
      "cinemas": [
        7,
        11,
        13,
        17,
        26
      ]
    },
    {
      "id": 1129895,
      "name": "Poslední střih",
      "screenings": 1,
      "posterUrl": "https://image.pmgstatic.com/cache/resized/w140/files/images/film/posters/166/690/166690693_bfc806.jpg",
      "cinemas": [
        16
      ]
    },
    {
      "id": 926338,
      "name": "Poslední závod",
      "screenings": 1,
      "posterUrl": "https://image.pmgstatic.com/cache/resized/w140/files/images/film/posters/165/981/165981700_e432cb.png",
      "cinemas": [
        11
      ]
    },
    {
      "id": 36858,
      "name": "Poznamenané děti",
      "screenings": 1,
      "posterUrl": "data:image/gif;base64,R0lGODlhAQABAIAAAAAAAP///yH5BAEAAAAALAAAAAABAAEAAAIBRAA7",
      "cinemas": [
        22
      ]
    },
    {
      "id": 1056095,
      "name": "Přání k narozeninám",
      "screenings": 358,
      "posterUrl": "https://image.pmgstatic.com/cache/resized/w140/files/images/film/posters/166/918/166918847_4dfd8f.jpg",
      "cinemas": [
        0,
        1,
        3,
        4,
        5,
        6,
        7,
        8,
        9,
        10,
        11,
        18,
        19,
        23,
        26,
        28,
        29
      ]
    },
    {
      "id": 1000885,
      "name": "Příběh hrůzostrašné Eliz",
      "screenings": 1,
      "posterUrl": "https://image.pmgstatic.com/cache/resized/w140/files/images/film/posters/165/810/165810098_afbd8b.jpg",
      "cinemas": [
        17
      ]
    },
    {
      "id": 929516,
      "name": "Princezna zakletá v čase 2",
      "screenings": 41,
      "posterUrl": "https://image.pmgstatic.com/cache/resized/w140/files/images/film/posters/166/758/166758180_d86714.jpg",
      "cinemas": [
        1,
        4,
        5,
        7,
        8,
        10
      ]
    },
    {
      "id": 1195099,
      "name": "PSH Nekonečný příběh",
      "screenings": 1,
      "posterUrl": "https://image.pmgstatic.com/cache/resized/w140/files/images/film/posters/166/795/166795800_7e5957.jpg",
      "cinemas": [
        20
      ]
    },
    {
      "id": 1067096,
      "name": "Řeka",
      "screenings": 1,
      "posterUrl": "https://image.pmgstatic.com/cache/resized/w140/files/images/film/posters/166/468/166468264_f08970.jpg",
      "cinemas": [
        19
      ]
    },
    {
      "id": 1143534,
      "name": "Rimini",
      "screenings": 1,
      "posterUrl": "https://image.pmgstatic.com/cache/resized/w140/files/images/film/posters/166/676/166676935_da333d.jpg",
      "cinemas": [
        22
      ]
    },
    {
      "id": 116339,
      "name": "RRRrrrr!!!",
      "screenings": 1,
      "posterUrl": "https://image.pmgstatic.com/cache/resized/w140/files/images/film/posters/000/074/74555_dfdc07.jpg",
      "cinemas": [
        16
      ]
    },
    {
      "id": 7366,
      "name": "S tebou mě baví svět",
      "screenings": 1,
      "posterUrl": "https://image.pmgstatic.com/cache/resized/w140/files/images/film/posters/000/006/6989_435799.jpg",
      "cinemas": [
        15
      ]
    },
    {
      "id": 30994,
      "name": "Saulův syn",
      "screenings": 1,
      "posterUrl": "https://image.pmgstatic.com/cache/resized/w140/files/images/film/posters/160/489/160489109_05ab00.jpg",
      "cinemas": [
        24
      ]
    },
    {
      "id": 246497,
      "name": "Seriózní muž",
      "screenings": 1,
      "posterUrl": "https://image.pmgstatic.com/cache/resized/w140/files/images/film/posters/000/058/58430_f3346a.jpg",
      "cinemas": [
        15
      ]
    },
    {
      "id": 1147073,
      "name": "Sierra",
      "screenings": 1,
      "posterUrl": "https://image.pmgstatic.com/cache/resized/w140/files/images/film/posters/166/226/166226810_418993.jpg",
      "cinemas": [
        17
      ]
    },
    {
      "id": 1126398,
      "name": "Šílená noc",
      "screenings": 2,
      "posterUrl": "https://image.pmgstatic.com/cache/resized/w140/files/images/film/posters/166/886/166886789_90e753.jpg",
      "cinemas": [
        8
      ]
    },
    {
      "id": 6669,
      "name": "Skřivánci na niti",
      "screenings": 1,
      "posterUrl": "https://image.pmgstatic.com/cache/resized/w140/files/images/film/posters/166/001/166001531_01874c.jpg",
      "cinemas": [
        22
      ]
    },
    {
      "id": 22128,
      "name": "Slečinky z Rochefortu",
      "screenings": 1,
      "posterUrl": "https://image.pmgstatic.com/cache/resized/w140/files/images/film/posters/163/801/163801471_5ecc70.jpg",
      "cinemas": [
        22
      ]
    },
    {
      "id": 755861,
      "name": "Slovo",
      "screenings": 1,
      "posterUrl": "https://image.pmgstatic.com/cache/resized/w140/files/images/film/posters/166/428/166428926_335057.jpg",
      "cinemas": [
        21
      ]
    },
    {
      "id": 922196,
      "name": "Smraďoch – Život v Paříži",
      "screenings": 1,
      "posterUrl": "https://image.pmgstatic.com/cache/resized/w140/files/images/film/posters/164/852/164852417_8735cc.jpg",
      "cinemas": [
        25
      ]
    },
    {
      "id": 1037126,
      "name": "Šoumen krokodýl",
      "screenings": 1,
      "posterUrl": "https://image.pmgstatic.com/cache/resized/w140/files/images/film/posters/166/646/166646533_ba427a.jpg",
      "cinemas": [
        27
      ]
    },
    {
      "id": 1142582,
      "name": "Srdce dubu",
      "screenings": 3,
      "posterUrl": "https://image.pmgstatic.com/cache/resized/w140/files/images/film/posters/166/789/166789407_2df43c.jpg",
      "cinemas": [
        18,
        25
      ]
    },
    {
      "id": 992497,
      "name": "Srdeční záležitost",
      "screenings": 2,
      "posterUrl": "https://image.pmgstatic.com/cache/resized/w140/files/images/film/posters/166/966/166966664_bed448.jpg",
      "cinemas": [
        26
      ]
    },
    {
      "id": 14696,
      "name": "Šťastný to muž",
      "screenings": 1,
      "posterUrl": "https://image.pmgstatic.com/cache/resized/w140/files/images/film/posters/158/732/158732657_e294c3.jpg",
      "cinemas": [
        22
      ]
    },
    {
      "id": 1085792,
      "name": "Strachy v nás",
      "screenings": 5,
      "posterUrl": "https://image.pmgstatic.com/cache/resized/w140/files/images/film/posters/166/897/166897738_0d99dd.png",
      "cinemas": [
        14,
        18
      ]
    },
    {
      "id": 1170268,
      "name": "Svatý pavouk",
      "screenings": 1,
      "posterUrl": "https://image.pmgstatic.com/cache/resized/w140/files/images/film/posters/166/852/166852382_d289f0.jpg",
      "cinemas": [
        21
      ]
    },
    {
      "id": 1232863,
      "name": "Sword Art Online: Progressive - Kuraki Yuuyami no Scherzo",
      "screenings": 28,
      "posterUrl": "https://image.pmgstatic.com/cache/resized/w140/files/images/film/posters/166/629/166629734_fcfbee.jpg",
      "cinemas": [
        4,
        5,
        6,
        7
      ]
    },
    {
      "id": 32034,
      "name": "Tajemství",
      "screenings": 1,
      "posterUrl": "https://image.pmgstatic.com/cache/resized/w140/files/images/film/posters/166/214/166214816_03a530.jpg",
      "cinemas": [
        22
      ]
    },
    {
      "id": 21630,
      "name": "Tatarská poušť",
      "screenings": 1,
      "posterUrl": "https://image.pmgstatic.com/cache/resized/w140/files/images/film/posters/120/456/120456588_7d0614.jpg",
      "cinemas": [
        22
      ]
    },
    {
      "id": 416621,
      "name": "The Disaster Artist: Úžasný propadák",
      "screenings": 1,
      "posterUrl": "https://image.pmgstatic.com/cache/resized/w140/files/images/film/posters/162/667/162667598_cc7899.jpg",
      "cinemas": [
        16
      ]
    },
    {
      "id": 8752,
      "name": "The Doors",
      "screenings": 9,
      "posterUrl": "https://image.pmgstatic.com/cache/resized/w140/files/images/film/posters/166/966/166966531_59beaa.jpg",
      "cinemas": [
        2,
        11,
        14,
        15,
        17,
        20,
        21,
        24
      ]
    },
    {
      "id": 1244848,
      "name": "Ti, kteří tancují ve tmě",
      "screenings": 3,
      "posterUrl": "https://image.pmgstatic.com/cache/resized/w140/files/images/film/posters/166/867/166867616_ce9629.jpg",
      "cinemas": [
        16,
        18,
        26
      ]
    },
    {
      "id": 1227041,
      "name": "Tizian – říše barev",
      "screenings": 3,
      "posterUrl": "https://image.pmgstatic.com/cache/resized/w140/files/images/film/posters/166/947/166947149_a6677e.jpg",
      "cinemas": [
        15,
        24,
        27
      ]
    },
    {
      "id": 286035,
      "name": "Top Gun: Maverick",
      "screenings": 1,
      "posterUrl": "https://image.pmgstatic.com/cache/resized/w140/files/images/film/posters/166/313/166313694_26ebe2.jpg",
      "cinemas": [
        17
      ]
    },
    {
      "id": 4257,
      "name": "Toxický mstitel",
      "screenings": 1,
      "posterUrl": "https://image.pmgstatic.com/cache/resized/w140/files/images/film/posters/162/684/162684726_12542e.jpg",
      "cinemas": [
        16
      ]
    },
    {
      "id": 875719,
      "name": "Trojúhelník smutku",
      "screenings": 37,
      "posterUrl": "https://image.pmgstatic.com/cache/resized/w140/files/images/film/posters/166/634/166634455_f5b8eb.jpg",
      "cinemas": [
        0,
        2,
        7,
        15,
        17,
        21,
        24,
        25,
        30
      ]
    },
    {
      "id": 9568,
      "name": "Truman Show",
      "screenings": 1,
      "posterUrl": "https://image.pmgstatic.com/cache/resized/w140/files/images/film/posters/158/988/158988851_fc9f76.jpg",
      "cinemas": [
        15
      ]
    },
    {
      "id": 1149547,
      "name": "Tutanchamon – poslední výstava",
      "screenings": 1,
      "posterUrl": "https://image.pmgstatic.com/cache/resized/w140/files/images/film/posters/166/141/166141243_a8775e.jpg",
      "cinemas": [
        11
      ]
    },
    {
      "id": 4983,
      "name": "Ucho",
      "screenings": 1,
      "posterUrl": "https://image.pmgstatic.com/cache/resized/w140/files/images/film/posters/166/568/166568813_bf1547.jpg",
      "cinemas": [
        22
      ]
    },
    {
      "id": 1166975,
      "name": "UFO Švédsko",
      "screenings": 8,
      "posterUrl": "https://image.pmgstatic.com/cache/resized/w140/files/images/film/posters/167/078/167078289_f66689.jpg",
      "cinemas": [
        7,
        11,
        13,
        26
      ]
    },
    {
      "id": 10123,
      "name": "Ukradená vzducholoď",
      "screenings": 1,
      "posterUrl": "https://image.pmgstatic.com/cache/resized/w140/files/images/film/posters/166/793/166793785_a40585.png",
      "cinemas": [
        25
      ]
    },
    {
      "id": 102472,
      "name": "Upír aneb Podivné dobrodružství Davida Graye",
      "screenings": 1,
      "posterUrl": "https://image.pmgstatic.com/cache/resized/w140/files/images/film/posters/160/795/160795405_24a2f6.jpg",
      "cinemas": [
        22
      ]
    },
    {
      "id": 948902,
      "name": "Úžasný Mauric",
      "screenings": 234,
      "posterUrl": "https://image.pmgstatic.com/cache/resized/w140/files/images/film/posters/166/962/166962896_161ff0.jpg",
      "cinemas": [
        0,
        1,
        2,
        3,
        4,
        5,
        6,
        7,
        8,
        11,
        21,
        23,
        24,
        29
      ]
    },
    {
      "id": 914037,
      "name": "Vánoční příběh",
      "screenings": 25,
      "posterUrl": "https://image.pmgstatic.com/cache/resized/w140/files/images/film/posters/166/757/166757038_85676c.jpg",
      "cinemas": [
        0,
        1,
        3,
        4,
        5,
        6,
        8,
        18,
        26,
        32
      ]
    },
    {
      "id": 38993,
      "name": "Vášeň lásky",
      "screenings": 1,
      "posterUrl": "https://image.pmgstatic.com/cache/resized/w140/files/images/film/posters/160/044/160044065_33f40e.jpg",
      "cinemas": [
        22
      ]
    },
    {
      "id": 1143709,
      "name": "Ve znamení býka",
      "screenings": 1,
      "posterUrl": "https://image.pmgstatic.com/cache/resized/w140/files/images/film/posters/166/912/166912801_143e4e.jpg",
      "cinemas": [
        23
      ]
    },
    {
      "id": 1052401,
      "name": "Velká svoboda",
      "screenings": 3,
      "posterUrl": "https://image.pmgstatic.com/cache/resized/w140/files/images/film/posters/167/048/167048122_538b6d.jpg",
      "cinemas": [
        11,
        15,
        24
      ]
    },
    {
      "id": 825127,
      "name": "Víly z Inisherinu",
      "screenings": 9,
      "posterUrl": "https://image.pmgstatic.com/cache/resized/w140/files/images/film/posters/167/001/167001040_ec170f.jpg",
      "cinemas": [
        11,
        23,
        24
      ]
    },
    {
      "id": 1066744,
      "name": "Vražda v Londýně",
      "screenings": 2,
      "posterUrl": "https://image.pmgstatic.com/cache/resized/w140/files/images/film/posters/166/757/166757721_3a833e.png",
      "cinemas": [
        11,
        27
      ]
    },
    {
      "id": 865902,
      "name": "Všechno, všude, najednou",
      "screenings": 6,
      "posterUrl": "https://image.pmgstatic.com/cache/resized/w140/files/images/film/posters/166/444/166444922_6930c4.jpg",
      "cinemas": [
        15,
        24
      ]
    },
    {
      "id": 1166972,
      "name": "Všechny mé dopisy spal",
      "screenings": 9,
      "posterUrl": "https://image.pmgstatic.com/cache/resized/w140/files/images/film/posters/167/065/167065868_f52af9.jpg",
      "cinemas": [
        7,
        13,
        18,
        19,
        23,
        26
      ]
    },
    {
      "id": 1131217,
      "name": "Vymývání mozku: Pohlaví-kamera-moc",
      "screenings": 1,
      "posterUrl": "https://image.pmgstatic.com/cache/resized/w140/files/images/film/posters/166/850/166850954_f71a9e.jpg",
      "cinemas": [
        24
      ]
    },
    {
      "id": 912147,
      "name": "Vyšehrad: Fylm",
      "screenings": 1,
      "posterUrl": "https://image.pmgstatic.com/cache/resized/w140/files/images/film/posters/166/067/166067240_2de18b.jpg",
      "cinemas": [
        23
      ]
    },
    {
      "id": 976646,
      "name": "Websterovi ve filmu",
      "screenings": 1,
      "posterUrl": "https://image.pmgstatic.com/cache/resized/w140/files/images/film/posters/166/420/166420837_ba8597.jpg",
      "cinemas": [
        22
      ]
    },
    {
      "id": 1111063,
      "name": "Whitney Houston: I Wanna Dance with Somebody",
      "screenings": 115,
      "posterUrl": "https://image.pmgstatic.com/cache/resized/w140/files/images/film/posters/166/997/166997463_409876.jpg",
      "cinemas": [
        0,
        1,
        3,
        4,
        5,
        6,
        7,
        8,
        18,
        19,
        24,
        27
      ]
    },
    {
      "id": 1250318,
      "name": "Za jak dlouho začnou pejska pálit tlapičky když vystoupí na dálnici",
      "screenings": 1,
      "posterUrl": "data:image/gif;base64,R0lGODlhAQABAIAAAAAAAP///yH5BAEAAAAALAAAAAABAAEAAAIBRAA7",
      "cinemas": [
        22
      ]
    },
    {
      "id": 1219970,
      "name": "Za vším hledej ženu",
      "screenings": 3,
      "posterUrl": "https://image.pmgstatic.com/cache/resized/w140/files/images/film/posters/166/648/166648038_1fbf5f.jpg",
      "cinemas": [
        18,
        26,
        32
      ]
    },
    {
      "id": 47568,
      "name": "Zaprodán",
      "screenings": 1,
      "posterUrl": "data:image/gif;base64,R0lGODlhAQABAIAAAAAAAP///yH5BAEAAAAALAAAAAABAAEAAAIBRAA7",
      "cinemas": [
        22
      ]
    },
    {
      "id": 6261,
      "name": "Zběsilost v srdci",
      "screenings": 1,
      "posterUrl": "https://image.pmgstatic.com/cache/resized/w140/files/images/film/posters/162/359/162359354_a037a1.jpg",
      "cinemas": [
        11
      ]
    },
    {
      "id": 266611,
      "name": "Ženy v pokušení",
      "screenings": 1,
      "posterUrl": "https://image.pmgstatic.com/cache/resized/w140/files/images/film/posters/000/062/62980_bd3e1e.jpg",
      "cinemas": [
        15
      ]
    },
    {
      "id": 250264,
      "url": "https://www.csfd.cz/film/250264-zivot-neni-krasny/",
      "name": "Život není krásný",
      "screenings": {
        "Praha - Rock Café": [
          "2023-02-18T16:00:00.000Z"
        ]
      }
    },
    {
      "id": 1195197,
      "name": "Zkouška umění",
      "screenings": 1,
      "posterUrl": "https://image.pmgstatic.com/cache/resized/w140/files/images/film/posters/166/467/166467546_bdd7c4.jpg",
      "cinemas": [
        24
      ]
    },
    {
      "id": 163427,
      "name": "Žofka a její dobrodružství - Jak Žofka umožnila panu Mrožovi cestu na sever",
      "screenings": 8,
      "cinemas": [
        2,
        15
      ]
    },
    {
      "id": 1229007,
      "name": "Zoubková víla",
      "screenings": 183,
      "posterUrl": "https://image.pmgstatic.com/cache/resized/w140/files/images/film/posters/166/911/166911945_5ac06c.jpg",
      "cinemas": [
        0,
        3,
        4,
        5,
        6,
        7,
        8,
        9,
        10,
        11,
        23,
        28,
        29
      ]
    }
  ]
}